kalna/__init__.py
kalna/calculate.py
kalna/data_cleaning/preprocess.py
kalna/data_details/__init__.py
kalna/data_details/preprocess.py
kalna/visualizations/__init__.py
kalna/visualizations/dataset_view.py
kalna-0.0.9.dist-info/LICENSE
kalna-0.0.9.dist-info/METADATA
kalna-0.0.9.dist-info/WHEEL
kalna-0.0.9.dist-info/top_level.txt
kalna-0.0.9.dist-info/RECORD
