Metadata-Version: 2.1
Name: kalna
Version: 0.0.9
Summary: A package automating the ML pipelines
Home-page: 
Author: Sayantan Ghosh
Author-email: sayantanghosh.work@gmail.com
License: UNKNOWN
Keywords: package numbers calculations
Platform: UNKNOWN
Classifier: Programming Language :: Python :: 3
Classifier: Operating System :: OS Independent
Requires-Dist: numpy
Requires-Dist: pandas
Requires-Dist: sklearn
Requires-Dist: matplotlib
Requires-Dist: seaborn
